chainix/__init__.py
chainix/main.py
chainix-1.0.2.dist-info/METADATA
chainix-1.0.2.dist-info/WHEEL
chainix-1.0.2.dist-info/top_level.txt
chainix-1.0.2.dist-info/RECORD
