Metadata-Version: 2.4
Name: chainix
Version: 1.0.2
Summary: A client library for executing asynchronous chains on chainix.ai with custom function callbacks
Home-page: https://github.com/ChainixDev/chainix-python
Author: Chainix
Author-email: jack@chainix.ai
Classifier: Programming Language :: Python :: 3
Classifier: License :: OSI Approved :: MIT License
Classifier: Operating System :: OS Independent
Requires-Python: >=3.7
Requires-Dist: requests>=2.25.0
Dynamic: author
Dynamic: author-email
Dynamic: classifier
Dynamic: description
Dynamic: description-content-type
Dynamic: home-page
Dynamic: requires-dist
Dynamic: requires-python
Dynamic: summary
